blspy.cpython-310-darwin.so
blspy-2.0.3.dist-info/RECORD
blspy-2.0.3.dist-info/LICENSE
blspy-2.0.3.dist-info/WHEEL
blspy-2.0.3.dist-info/top_level.txt
blspy-2.0.3.dist-info/METADATA
