Metadata-Version: 2.1
Name: blspy
Version: 2.0.3
Summary: BLS signatures in c++ (python bindings)
Home-page: https://github.com/Chia-Network/bls-signatures
Author: Mariano Sorgente
Author-email: mariano@chia.net
Requires-Python: >=3.7
License-File: LICENSE
Requires-Dist: wheel
